{
  "language": "kalba",
  "form": {
    "warning": "Translation may not be correct, help us fix. Contact",
    "write_letter": "Rašyti laišką",
    "subject": "Laiškas Santa Klausui",
    "use_template": "naudoti šabloną",
    "name": "vardas",
    "letter": "laišką",
    "close": "Uždaryti",
    "send": "siųsti",
    "sending": "siunčiama",
    "sent": "laiškas išsiųstas!",
    "sending_failed": "išsiųsti nepavyko",
    "letter_text": {
      "parent_email": "tėvų El-paštas",
      "wish": "norai",
      "letter_text": "laiško tekstas",
      "dear_santa": "Gerbiamas Santa",
      "my_name_is": "Mano vardas yra",
      "doing_well": "Tikiuosi, kad tau gerai sekasi.",
      "good_this_year": "Šiais metais stengiausi būti geras",
      "ask_parents": "apie tai galite paklausti mano tėvų, su jais galite susisiekti el. ",
      "gift_this_christmas": "Šias Kalėdas norėčiau gauti",
      "merry_christmas_happy_new_year": "Linksmų Šv. Kalėdų ir laimingų Naujųjų metų!",
      "with_love": "Su meile"
    }
  },
  "meta_data": {
    "title": "Siųsti laišką Santa Klausui!",
    "description": "Mielas Santa Klausai: Siųskite Kalėdų / Naujųjų metų linkėjimus čia!"
  }
}
